pychrone/__init__.py
test/__init__.py
test/test_pychrone.py
pychrone-0.0.3.dist-info/LICENSE
pychrone-0.0.3.dist-info/METADATA
pychrone-0.0.3.dist-info/WHEEL
pychrone-0.0.3.dist-info/top_level.txt
pychrone-0.0.3.dist-info/RECORD
