Metadata-Version: 2.1
Name: pychrone
Version: 0.0.3
Summary: Small python module for building isochrones
Home-page: https://github.com/headshaker/pychrone
Author: Nikita Chistikov
Author-email: chistikov@gmail.com
License: UNKNOWN
Platform: UNKNOWN
Classifier: Programming Language :: Python :: 3
Classifier: License :: OSI Approved :: MIT License
Classifier: Operating System :: OS Independent
